[
  {
    "package": "ribd",
    "oncran": true
  },
  {
    "package": "paramlink",
    "oncran": true
  },
  {
    "package": "pedmut",
    "oncran": true
  },
  {
    "package": "pedtools",
    "oncran": true
  },
  {
    "package": "forrel",
    "oncran": true
  },
  {
    "package": "pedbuildr",
    "oncran": true
  },
  {
    "package": "paramlink2",
    "oncran": true
  },
  {
    "package": "ibdsim2",
    "oncran": true
  },
  {
    "package": "pedprobr",
    "oncran": true
  },
  {
    "package": "segregatr",
    "oncran": true
  },
  {
    "package": "pedsuite",
    "oncran": true
  },
  {
    "package": "verbalisr",
    "oncran": true
  }
]
